face2face/__init__.py
face2face/__main__.py
face2face/compatibility_check/check_compatibility.py
face2face/data/ICCSS17/metadata_ICCSS17.dat
face2face/data/ICCSS17/tij_ICCSS17.dat
face2face/data/Synthetic_Data/synthetic_metadata.dat
face2face/data/Synthetic_Data/synthetic_tij.dat
face2face/data/Test/meta_test.dat
face2face/data/Test/meta_test_header.dat
face2face/data/Test/tij_test.dat
face2face/data/Test/tij_test_header.dat
face2face/data/WS16/metadata_WS16.dat
face2face/data/WS16/tij_WS16.dat
face2face/data/WS16/tij_test.dat
face2face/imports/__init__.py
face2face/imports/create_network.py
face2face/imports/load_all_data.py
face2face/imports/test.py
face2face/statistics/__init__.py
face2face/statistics/average_degree.py
face2face/statistics/check_distribution.py
face2face/statistics/distribution.py
face2face/statistics/network_quantities.py
face2face/statistics/null_modell.py
face2face/visualization/__init__.py
face2face/visualization/output_network_information.py
face2face/visualization/plot_average_degree_group.py
face2face/visualization/plot_contact_matrix_heatmap.py
face2face/visualization/plot_histogram_null_model.py
face2face/visualization/plot_probability_distribution.py
face2face-0.2.1a0.dist-info/LICENSE
face2face-0.2.1a0.dist-info/LICENSE.rst
face2face-0.2.1a0.dist-info/METADATA
face2face-0.2.1a0.dist-info/WHEEL
face2face-0.2.1a0.dist-info/top_level.txt
face2face-0.2.1a0.dist-info/RECORD
