Metadata-Version: 2.1
Name: face2face
Version: 0.2.1.Alpha
Summary: Library with basic social science functions
Home-page: https://gesiscss.github.io/face2face/
Author: UNKNOWN
Author-email: UNKNOWN
License: GPLv3
Platform: UNKNOWN
Requires-Dist: numpy
Requires-Dist: pandas
Requires-Dist: matplotlib
Requires-Dist: networkx
Requires-Dist: scipy
Requires-Dist: seaborn
Requires-Dist: powerlaw
